{
    "RunTime": 361.453050387,
    "tests": {
        "0": {
            "MessageAdversaryPower": 1,
            "avgDeliveryNodes": 100.0,
            "avgDeliveryTime": 5.11340206185567,
            "byzantineNodes": [
                7,
                27,
                51
            ],
            "disconnectedNodes": [],
            "maxDeliveryTime": 6,
            "senderId": 0,
            "totalMsgsSent": 17818823
        },
        "1": {
            "MessageAdversaryPower": 1,
            "avgDeliveryNodes": 100.0,
            "avgDeliveryTime": 5.144329896907217,
            "byzantineNodes": [
                7,
                27,
                51
            ],
            "disconnectedNodes": [],
            "maxDeliveryTime": 6,
            "senderId": 0,
            "totalMsgsSent": 17367429
        },
        "10": {
            "MessageAdversaryPower": 1,
            "avgDeliveryNodes": 100.0,
            "avgDeliveryTime": 5.144329896907217,
            "byzantineNodes": [
                7,
                27,
                51
            ],
            "disconnectedNodes": [],
            "maxDeliveryTime": 6,
            "senderId": 0,
            "totalMsgsSent": 17553677
        },
        "11": {
            "MessageAdversaryPower": 1,
            "avgDeliveryNodes": 100.0,
            "avgDeliveryTime": 5.11340206185567,
            "byzantineNodes": [
                7,
                27,
                51
            ],
            "disconnectedNodes": [],
            "maxDeliveryTime": 6,
            "senderId": 0,
            "totalMsgsSent": 17228288
        },
        "12": {
            "MessageAdversaryPower": 1,
            "avgDeliveryNodes": 100.0,
            "avgDeliveryTime": 5.144329896907217,
            "byzantineNodes": [
                7,
                27,
                51
            ],
            "disconnectedNodes": [],
            "maxDeliveryTime": 6,
            "senderId": 0,
            "totalMsgsSent": 16773586
        },
        "13": {
            "MessageAdversaryPower": 1,
            "avgDeliveryNodes": 100.0,
            "avgDeliveryTime": 5.206185567010309,
            "byzantineNodes": [
                7,
                27,
                51
            ],
            "disconnectedNodes": [],
            "maxDeliveryTime": 6,
            "senderId": 0,
            "totalMsgsSent": 18095783
        },
        "14": {
            "MessageAdversaryPower": 1,
            "avgDeliveryNodes": 100.0,
            "avgDeliveryTime": 5.134020618556701,
            "byzantineNodes": [
                7,
                27,
                51
            ],
            "disconnectedNodes": [],
            "maxDeliveryTime": 6,
            "senderId": 0,
            "totalMsgsSent": 17550208
        },
        "15": {
            "MessageAdversaryPower": 1,
            "avgDeliveryNodes": 100.0,
            "avgDeliveryTime": 5.134020618556701,
            "byzantineNodes": [
                7,
                27,
                51
            ],
            "disconnectedNodes": [],
            "maxDeliveryTime": 6,
            "senderId": 0,
            "totalMsgsSent": 17555633
        },
        "16": {
            "MessageAdversaryPower": 1,
            "avgDeliveryNodes": 100.0,
            "avgDeliveryTime": 5.123711340206185,
            "byzantineNodes": [
                7,
                27,
                51
            ],
            "disconnectedNodes": [],
            "maxDeliveryTime": 6,
            "senderId": 0,
            "totalMsgsSent": 17168532
        },
        "17": {
            "MessageAdversaryPower": 1,
            "avgDeliveryNodes": 100.0,
            "avgDeliveryTime": 5.103092783505154,
            "byzantineNodes": [
                7,
                27,
                51
            ],
            "disconnectedNodes": [],
            "maxDeliveryTime": 6,
            "senderId": 0,
            "totalMsgsSent": 17818787
        },
        "18": {
            "MessageAdversaryPower": 1,
            "avgDeliveryNodes": 100.0,
            "avgDeliveryTime": 5.082474226804123,
            "byzantineNodes": [
                7,
                27,
                51
            ],
            "disconnectedNodes": [],
            "maxDeliveryTime": 6,
            "senderId": 0,
            "totalMsgsSent": 17343750
        },
        "19": {
            "MessageAdversaryPower": 1,
            "avgDeliveryNodes": 100.0,
            "avgDeliveryTime": 5.134020618556701,
            "byzantineNodes": [
                7,
                27,
                51
            ],
            "disconnectedNodes": [],
            "maxDeliveryTime": 6,
            "senderId": 0,
            "totalMsgsSent": 17362534
        },
        "2": {
            "MessageAdversaryPower": 1,
            "avgDeliveryNodes": 100.0,
            "avgDeliveryTime": 5.123711340206185,
            "byzantineNodes": [
                7,
                27,
                51
            ],
            "disconnectedNodes": [],
            "maxDeliveryTime": 6,
            "senderId": 0,
            "totalMsgsSent": 17414640
        },
        "20": {
            "MessageAdversaryPower": 1,
            "avgDeliveryNodes": 100.0,
            "avgDeliveryTime": 5.123711340206185,
            "byzantineNodes": [
                7,
                27,
                51
            ],
            "disconnectedNodes": [],
            "maxDeliveryTime": 6,
            "senderId": 0,
            "totalMsgsSent": 17550425
        },
        "21": {
            "MessageAdversaryPower": 1,
            "avgDeliveryNodes": 100.0,
            "avgDeliveryTime": 5.206185567010309,
            "byzantineNodes": [
                7,
                27,
                51
            ],
            "disconnectedNodes": [],
            "maxDeliveryTime": 6,
            "senderId": 0,
            "totalMsgsSent": 16805496
        },
        "22": {
            "MessageAdversaryPower": 1,
            "avgDeliveryNodes": 100.0,
            "avgDeliveryTime": 5.206185567010309,
            "byzantineNodes": [
                7,
                27,
                51
            ],
            "disconnectedNodes": [],
            "maxDeliveryTime": 6,
            "senderId": 0,
            "totalMsgsSent": 17979717
        },
        "23": {
            "MessageAdversaryPower": 1,
            "avgDeliveryNodes": 100.0,
            "avgDeliveryTime": 5.154639175257732,
            "byzantineNodes": [
                7,
                27,
                51
            ],
            "disconnectedNodes": [],
            "maxDeliveryTime": 6,
            "senderId": 0,
            "totalMsgsSent": 17762791
        },
        "24": {
            "MessageAdversaryPower": 1,
            "avgDeliveryNodes": 100.0,
            "avgDeliveryTime": 5.123711340206185,
            "byzantineNodes": [
                7,
                27,
                51
            ],
            "disconnectedNodes": [],
            "maxDeliveryTime": 6,
            "senderId": 0,
            "totalMsgsSent": 17947330
        },
        "3": {
            "MessageAdversaryPower": 1,
            "avgDeliveryNodes": 100.0,
            "avgDeliveryTime": 5.154639175257732,
            "byzantineNodes": [
                7,
                27,
                51
            ],
            "disconnectedNodes": [],
            "maxDeliveryTime": 6,
            "senderId": 0,
            "totalMsgsSent": 18294581
        },
        "4": {
            "MessageAdversaryPower": 1,
            "avgDeliveryNodes": 100.0,
            "avgDeliveryTime": 5.11340206185567,
            "byzantineNodes": [
                7,
                27,
                51
            ],
            "disconnectedNodes": [],
            "maxDeliveryTime": 6,
            "senderId": 0,
            "totalMsgsSent": 17814193
        },
        "5": {
            "MessageAdversaryPower": 1,
            "avgDeliveryNodes": 100.0,
            "avgDeliveryTime": 5.072164948453608,
            "byzantineNodes": [
                7,
                27,
                51
            ],
            "disconnectedNodes": [],
            "maxDeliveryTime": 6,
            "senderId": 0,
            "totalMsgsSent": 17606608
        },
        "6": {
            "MessageAdversaryPower": 1,
            "avgDeliveryNodes": 100.0,
            "avgDeliveryTime": 5.144329896907217,
            "byzantineNodes": [
                7,
                27,
                51
            ],
            "disconnectedNodes": [],
            "maxDeliveryTime": 6,
            "senderId": 0,
            "totalMsgsSent": 17616001
        },
        "7": {
            "MessageAdversaryPower": 1,
            "avgDeliveryNodes": 100.0,
            "avgDeliveryTime": 5.11340206185567,
            "byzantineNodes": [
                7,
                27,
                51
            ],
            "disconnectedNodes": [],
            "maxDeliveryTime": 6,
            "senderId": 0,
            "totalMsgsSent": 17548318
        },
        "8": {
            "MessageAdversaryPower": 1,
            "avgDeliveryNodes": 100.0,
            "avgDeliveryTime": 5.164948453608248,
            "byzantineNodes": [
                7,
                27,
                51
            ],
            "disconnectedNodes": [],
            "maxDeliveryTime": 6,
            "senderId": 0,
            "totalMsgsSent": 18014503
        },
        "9": {
            "MessageAdversaryPower": 1,
            "avgDeliveryNodes": 100.0,
            "avgDeliveryTime": 5.103092783505154,
            "byzantineNodes": [
                7,
                27,
                51
            ],
            "disconnectedNodes": [],
            "maxDeliveryTime": 6,
            "senderId": 0,
            "totalMsgsSent": 17746371
        }
    }
}
