{
    "RunTime": 295.063845927,
    "tests": {
        "0": {
            "MessageAdversaryPower": 0,
            "avgDeliveryNodes": 100.0,
            "avgDeliveryTime": 5.010416666666667,
            "byzantineNodes": [
                2,
                75,
                84,
                88
            ],
            "disconnectedNodes": [],
            "maxDeliveryTime": 6,
            "senderId": 0,
            "totalMsgsSent": 12279812
        },
        "1": {
            "MessageAdversaryPower": 0,
            "avgDeliveryNodes": 100.0,
            "avgDeliveryTime": 5.010416666666667,
            "byzantineNodes": [
                2,
                75,
                84,
                88
            ],
            "disconnectedNodes": [],
            "maxDeliveryTime": 6,
            "senderId": 0,
            "totalMsgsSent": 12279812
        },
        "10": {
            "MessageAdversaryPower": 0,
            "avgDeliveryNodes": 100.0,
            "avgDeliveryTime": 5.010416666666667,
            "byzantineNodes": [
                2,
                75,
                84,
                88
            ],
            "disconnectedNodes": [],
            "maxDeliveryTime": 6,
            "senderId": 0,
            "totalMsgsSent": 12279812
        },
        "11": {
            "MessageAdversaryPower": 0,
            "avgDeliveryNodes": 100.0,
            "avgDeliveryTime": 5.010416666666667,
            "byzantineNodes": [
                2,
                75,
                84,
                88
            ],
            "disconnectedNodes": [],
            "maxDeliveryTime": 6,
            "senderId": 0,
            "totalMsgsSent": 12279812
        },
        "12": {
            "MessageAdversaryPower": 0,
            "avgDeliveryNodes": 100.0,
            "avgDeliveryTime": 5.010416666666667,
            "byzantineNodes": [
                2,
                75,
                84,
                88
            ],
            "disconnectedNodes": [],
            "maxDeliveryTime": 6,
            "senderId": 0,
            "totalMsgsSent": 12279812
        },
        "13": {
            "MessageAdversaryPower": 0,
            "avgDeliveryNodes": 100.0,
            "avgDeliveryTime": 5.010416666666667,
            "byzantineNodes": [
                2,
                75,
                84,
                88
            ],
            "disconnectedNodes": [],
            "maxDeliveryTime": 6,
            "senderId": 0,
            "totalMsgsSent": 12279812
        },
        "14": {
            "MessageAdversaryPower": 0,
            "avgDeliveryNodes": 100.0,
            "avgDeliveryTime": 5.010416666666667,
            "byzantineNodes": [
                2,
                75,
                84,
                88
            ],
            "disconnectedNodes": [],
            "maxDeliveryTime": 6,
            "senderId": 0,
            "totalMsgsSent": 12279812
        },
        "15": {
            "MessageAdversaryPower": 0,
            "avgDeliveryNodes": 100.0,
            "avgDeliveryTime": 5.010416666666667,
            "byzantineNodes": [
                2,
                75,
                84,
                88
            ],
            "disconnectedNodes": [],
            "maxDeliveryTime": 6,
            "senderId": 0,
            "totalMsgsSent": 12279812
        },
        "16": {
            "MessageAdversaryPower": 0,
            "avgDeliveryNodes": 100.0,
            "avgDeliveryTime": 5.010416666666667,
            "byzantineNodes": [
                2,
                75,
                84,
                88
            ],
            "disconnectedNodes": [],
            "maxDeliveryTime": 6,
            "senderId": 0,
            "totalMsgsSent": 12279812
        },
        "17": {
            "MessageAdversaryPower": 0,
            "avgDeliveryNodes": 100.0,
            "avgDeliveryTime": 5.010416666666667,
            "byzantineNodes": [
                2,
                75,
                84,
                88
            ],
            "disconnectedNodes": [],
            "maxDeliveryTime": 6,
            "senderId": 0,
            "totalMsgsSent": 12279812
        },
        "18": {
            "MessageAdversaryPower": 0,
            "avgDeliveryNodes": 100.0,
            "avgDeliveryTime": 5.010416666666667,
            "byzantineNodes": [
                2,
                75,
                84,
                88
            ],
            "disconnectedNodes": [],
            "maxDeliveryTime": 6,
            "senderId": 0,
            "totalMsgsSent": 12279812
        },
        "19": {
            "MessageAdversaryPower": 0,
            "avgDeliveryNodes": 100.0,
            "avgDeliveryTime": 5.010416666666667,
            "byzantineNodes": [
                2,
                75,
                84,
                88
            ],
            "disconnectedNodes": [],
            "maxDeliveryTime": 6,
            "senderId": 0,
            "totalMsgsSent": 12279812
        },
        "2": {
            "MessageAdversaryPower": 0,
            "avgDeliveryNodes": 100.0,
            "avgDeliveryTime": 5.010416666666667,
            "byzantineNodes": [
                2,
                75,
                84,
                88
            ],
            "disconnectedNodes": [],
            "maxDeliveryTime": 6,
            "senderId": 0,
            "totalMsgsSent": 12279812
        },
        "20": {
            "MessageAdversaryPower": 0,
            "avgDeliveryNodes": 100.0,
            "avgDeliveryTime": 5.010416666666667,
            "byzantineNodes": [
                2,
                75,
                84,
                88
            ],
            "disconnectedNodes": [],
            "maxDeliveryTime": 6,
            "senderId": 0,
            "totalMsgsSent": 12279812
        },
        "21": {
            "MessageAdversaryPower": 0,
            "avgDeliveryNodes": 100.0,
            "avgDeliveryTime": 5.010416666666667,
            "byzantineNodes": [
                2,
                75,
                84,
                88
            ],
            "disconnectedNodes": [],
            "maxDeliveryTime": 6,
            "senderId": 0,
            "totalMsgsSent": 12279812
        },
        "22": {
            "MessageAdversaryPower": 0,
            "avgDeliveryNodes": 100.0,
            "avgDeliveryTime": 5.010416666666667,
            "byzantineNodes": [
                2,
                75,
                84,
                88
            ],
            "disconnectedNodes": [],
            "maxDeliveryTime": 6,
            "senderId": 0,
            "totalMsgsSent": 12279812
        },
        "23": {
            "MessageAdversaryPower": 0,
            "avgDeliveryNodes": 100.0,
            "avgDeliveryTime": 5.010416666666667,
            "byzantineNodes": [
                2,
                75,
                84,
                88
            ],
            "disconnectedNodes": [],
            "maxDeliveryTime": 6,
            "senderId": 0,
            "totalMsgsSent": 12279812
        },
        "24": {
            "MessageAdversaryPower": 0,
            "avgDeliveryNodes": 100.0,
            "avgDeliveryTime": 5.010416666666667,
            "byzantineNodes": [
                2,
                75,
                84,
                88
            ],
            "disconnectedNodes": [],
            "maxDeliveryTime": 6,
            "senderId": 0,
            "totalMsgsSent": 12279812
        },
        "3": {
            "MessageAdversaryPower": 0,
            "avgDeliveryNodes": 100.0,
            "avgDeliveryTime": 5.010416666666667,
            "byzantineNodes": [
                2,
                75,
                84,
                88
            ],
            "disconnectedNodes": [],
            "maxDeliveryTime": 6,
            "senderId": 0,
            "totalMsgsSent": 12279812
        },
        "4": {
            "MessageAdversaryPower": 0,
            "avgDeliveryNodes": 100.0,
            "avgDeliveryTime": 5.010416666666667,
            "byzantineNodes": [
                2,
                75,
                84,
                88
            ],
            "disconnectedNodes": [],
            "maxDeliveryTime": 6,
            "senderId": 0,
            "totalMsgsSent": 12279812
        },
        "5": {
            "MessageAdversaryPower": 0,
            "avgDeliveryNodes": 100.0,
            "avgDeliveryTime": 5.010416666666667,
            "byzantineNodes": [
                2,
                75,
                84,
                88
            ],
            "disconnectedNodes": [],
            "maxDeliveryTime": 6,
            "senderId": 0,
            "totalMsgsSent": 12279812
        },
        "6": {
            "MessageAdversaryPower": 0,
            "avgDeliveryNodes": 100.0,
            "avgDeliveryTime": 5.010416666666667,
            "byzantineNodes": [
                2,
                75,
                84,
                88
            ],
            "disconnectedNodes": [],
            "maxDeliveryTime": 6,
            "senderId": 0,
            "totalMsgsSent": 12279812
        },
        "7": {
            "MessageAdversaryPower": 0,
            "avgDeliveryNodes": 100.0,
            "avgDeliveryTime": 5.010416666666667,
            "byzantineNodes": [
                2,
                75,
                84,
                88
            ],
            "disconnectedNodes": [],
            "maxDeliveryTime": 6,
            "senderId": 0,
            "totalMsgsSent": 12279812
        },
        "8": {
            "MessageAdversaryPower": 0,
            "avgDeliveryNodes": 100.0,
            "avgDeliveryTime": 5.010416666666667,
            "byzantineNodes": [
                2,
                75,
                84,
                88
            ],
            "disconnectedNodes": [],
            "maxDeliveryTime": 6,
            "senderId": 0,
            "totalMsgsSent": 12279812
        },
        "9": {
            "MessageAdversaryPower": 0,
            "avgDeliveryNodes": 100.0,
            "avgDeliveryTime": 5.010416666666667,
            "byzantineNodes": [
                2,
                75,
                84,
                88
            ],
            "disconnectedNodes": [],
            "maxDeliveryTime": 6,
            "senderId": 0,
            "totalMsgsSent": 12279812
        }
    }
}
